{
  "cards": {
    "mm1qpy4vbw0bpqjtxrn": {
      "id": "mm1qpy4vbw0bpqjtxrn",
      "col": 3,
      "topRowFrac": 1,
      "heightFrac": 1,
      "text": "Dev- WarmUp",
      "color": "#caffbf"
    },
    "mm1qrk9evrqma7jm4c": {
      "id": "mm1qrk9evrqma7jm4c",
      "col": 3,
      "topRowFrac": 2,
      "heightFrac": 2.5,
      "text": "Unity - Paper Discussion Writing",
      "color": "#e0bbff"
    },
    "mm1qtt9rp4c461g6bv": {
      "id": "mm1qtt9rp4c461g6bv",
      "col": 3,
      "topRowFrac": 4.5,
      "heightFrac": 1.5,
      "text": "Mittag",
      "color": "#fdffb6"
    }
  }
}